mcp_server_dpipblock/__init__.py
mcp_server_dpipblock/__main__.py
mcp_server_dpipblock/server.py
mcp_server_dpipblock/test.py
dpipblock-0.1.0.dist-info/METADATA
dpipblock-0.1.0.dist-info/WHEEL
dpipblock-0.1.0.dist-info/top_level.txt
dpipblock-0.1.0.dist-info/RECORD
