Metadata-Version: 2.4
Name: dpipblock
Version: 0.1.0
Summary: Add your description here
Requires-Python: >=3.10
Requires-Dist: ddddocr>=1.5.6
Requires-Dist: mcp>=1.9.1
Requires-Dist: pydantic>=2.11.5
Requires-Dist: pyexecjs>=1.5.1
Requires-Dist: pytest>=8.3.5
Requires-Dist: requests>=2.32.3
